cognite/utils/__init__.py
cognite/utils/_logging.py
cognite/utils/contextualization/__init__.py
cognite/utils/contextualization/_entity_match_categorizer.py
cognite/utils/infrastructure/__init__.py
cognite/utils/infrastructure/_cdf_project_archiver.py
cognite_utils-0.1.1.dist-info/LICENSE
cognite_utils-0.1.1.dist-info/WHEEL
cognite_utils-0.1.1.dist-info/METADATA
cognite_utils-0.1.1.dist-info/RECORD
