Metadata-Version: 2.1
Name: cognite-utils
Version: 0.1.1
Summary: Python Utilities Extending the Use of Cognite Products
Home-page: https://cognitedata.github.io/cognite-python-utils/
License: Apache-2.0
Author: Sangyoon Park
Author-email: sangyoon.park@cognite.com
Requires-Python: >=3.8,<4.0
Classifier: License :: OSI Approved :: Apache Software License
Classifier: Programming Language :: Python :: 3
Classifier: Programming Language :: Python :: 3.8
Classifier: Programming Language :: Python :: 3.9
Classifier: Programming Language :: Python :: 3.10
Classifier: Programming Language :: Python :: 3.11
Requires-Dist: cognite-sdk (>=4.11.3,<5.0.0)
Requires-Dist: cognite-sdk-experimental (>=0.107.0,<0.108.0)
Requires-Dist: numpy (>=1.23.5,<2.0.0)
Requires-Dist: pandas (>=1.5.2,<2.0.0)
Project-URL: Repository, https://github.com/cognitedata/cognite-python-utils
